templatestring/__init__.py
templatestring-0.1.0.dist-info/METADATA
templatestring-0.1.0.dist-info/WHEEL
templatestring-0.1.0.dist-info/RECORD
